redfish/__init__.py
redfish/security_masking.py
redfish/hpilo/__init__.py
redfish/hpilo/risblobstore2.py
redfish/hpilo/rishpilo.py
redfish/hpilo/vnichpilo.py
redfish/rest/__init__.py
redfish/rest/connections.py
redfish/rest/containers.py
redfish/rest/v1.py
redfish/ris/__init__.py
redfish/ris/gen_compat.py
redfish/ris/resp_handler.py
redfish/ris/ris.py
redfish/ris/ris_threaded.py
redfish/ris/rmc.py
redfish/ris/rmc_api.py
redfish/ris/rmc_helper.py
redfish/ris/sharedtypes.py
redfish/ris/utils.py
redfish/ris/validation.py
python_ilorest_library-7.0.0.0.dist-info/LICENSE
python_ilorest_library-7.0.0.0.dist-info/METADATA
python_ilorest_library-7.0.0.0.dist-info/WHEEL
python_ilorest_library-7.0.0.0.dist-info/top_level.txt
python_ilorest_library-7.0.0.0.dist-info/RECORD
