Metadata-Version: 2.1
Name: python-ilorest-library
Version: 7.0.0.0
Summary: iLO Rest Python Library
Home-page: https://github.com/HewlettPackard/python-ilorest-library
Author: Hewlett Packard Enterprise
Author-email: rajeevalochana.kallur@hpe.com
Keywords: Hewlett Packard Enterprise
Classifier: Development Status :: 5 - Production/Stable
Classifier: License :: OSI Approved :: Apache Software License
Classifier: Programming Language :: Python :: 3.8
Classifier: Programming Language :: Python :: 3.9
Classifier: Programming Language :: Python :: 3.10
Classifier: Programming Language :: Python :: 3.11
Classifier: Programming Language :: Python :: 3.12
Classifier: Topic :: Communications
License-File: LICENSE
Requires-Dist: jsonpatch
Requires-Dist: jsonpath-rw
Requires-Dist: jsonpointer
Requires-Dist: urllib3
Requires-Dist: six
